link/__init__.py
link/middleware/__init__.py
link/middleware/confdriver.py
link/middleware/connectable.py
link/middleware/core.py
link/middleware/file.py
link/middleware/http.py
link/middleware/socket.py
link/middleware/tcp.py
link/middleware/udp.py
link/middleware/test/__init__.py
link/middleware/test/connectable.py
link/middleware/test/core.py
link/middleware/test/file.py
link/middleware/test/http.py
link/middleware/test/socket.py
link/middleware/test/tcp.py
link/middleware/test/udp.py
link.middleware-1.5.dist-info/DESCRIPTION.rst
link.middleware-1.5.dist-info/METADATA
link.middleware-1.5.dist-info/RECORD
link.middleware-1.5.dist-info/WHEEL
link.middleware-1.5.dist-info/metadata.json
link.middleware-1.5.dist-info/top_level.txt
