Metadata-Version: 2.0
Name: link.middleware
Version: 1.5
Summary: Provides utilities to make middlewares connecting to a remote service
Home-page: https://github.com/linkdd/link.middleware
Author: David Delassus
Author-email: david.jose.delassus@gmail.com
License: MIT
Keywords: link middleware
Platform: UNKNOWN
Classifier: Development Status :: 5 - Production/Stable
Classifier: License :: OSI Approved :: MIT License
Classifier: Operating System :: OS Independent
Classifier: Topic :: Utilities
Classifier: Topic :: Software Development :: Libraries :: Python Modules
Classifier: Intended Audience :: Developers
Classifier: Programming Language :: Python
Classifier: Programming Language :: Python :: 2.7
Classifier: Programming Language :: Python :: 3
Classifier: Programming Language :: Python :: 3.4
Classifier: Programming Language :: Python :: 3.5
Classifier: Programming Language :: Python :: Implementation :: CPython
Requires-Dist: b3j0f.utils (>=1.4.3)
Requires-Dist: link.feature (>=2.1)
Requires-Dist: mock (>=2.0.0)
Requires-Dist: requests (>=2.10.0)
